dirstat.py
dirstat-0.1.2.dist-info/licenses/LICENSE.txt
dirstat-0.1.2.dist-info/METADATA
dirstat-0.1.2.dist-info/WHEEL
dirstat-0.1.2.dist-info/entry_points.txt
dirstat-0.1.2.dist-info/top_level.txt
dirstat-0.1.2.dist-info/RECORD
