Metadata-Version: 2.4
Name: dirstat
Version: 0.1.2
Summary: A single-file no-dependency Python program (also usable as a library module) to efficiently gather directory statistics.
Author-email: Sébastien Hocquet <seb@ipamo.net>
Project-URL: Homepage, https://gitlab.com/ipamo/dirstat
Project-URL: Bug Tracker, https://gitlab.com/ipamo/dirstat/issues
Keywords: single,directory,statistics,dirstat,windirstat
Classifier: Development Status :: 5 - Production/Stable
Classifier: License :: OSI Approved :: MIT License
Classifier: Operating System :: OS Independent
Classifier: Programming Language :: Python :: 3
Classifier: Environment :: Console
Classifier: Topic :: Software Development :: Libraries
Requires-Python: >=3.7
License-File: LICENSE.txt
Dynamic: license-file
